axmp_ai_agent_core/__init__.py
axmp_ai_agent_core/agent/base_agent.py
axmp_ai_agent_core/agent/configuration.py
axmp_ai_agent_core/agent/default_agent.py
axmp_ai_agent_core/agent/langgraph_react_agent.py
axmp_ai_agent_core/agent/single_spec_agent.py
axmp_ai_agent_core/agent/state.py
axmp_ai_agent_core/agent/util/agent_cache.py
axmp_ai_agent_core/agent/util/agent_key_format.py
axmp_ai_agent_core/agent/util/chat_file_utils.py
axmp_ai_agent_core/agent/util/depends_on_utils.py
axmp_ai_agent_core/agent/util/graph_stream_utils.py
axmp_ai_agent_core/agent/util/load_chat_model.py
axmp_ai_agent_core/agent/util/mcp_client_manager.py
axmp_ai_agent_core/db/agent_profile_history_repository.py
axmp_ai_agent_core/db/agent_profile_repository.py
axmp_ai_agent_core/db/base_repository.py
axmp_ai_agent_core/db/chat_file_repository.py
axmp_ai_agent_core/db/chat_memory_repository.py
axmp_ai_agent_core/db/conversation_repository.py
axmp_ai_agent_core/db/group_repository.py
axmp_ai_agent_core/db/llm_provider_repository.py
axmp_ai_agent_core/db/user_credential_repository.py
axmp_ai_agent_core/db/user_repository.py
axmp_ai_agent_core/dto/list_response_model.py
axmp_ai_agent_core/dto/response_model.py
axmp_ai_agent_core/entity/agent_profile.py
axmp_ai_agent_core/entity/agent_profile_history.py
axmp_ai_agent_core/entity/base_model.py
axmp_ai_agent_core/entity/base_profile.py
axmp_ai_agent_core/entity/chat_conversation.py
axmp_ai_agent_core/entity/chat_file.py
axmp_ai_agent_core/entity/chat_memory.py
axmp_ai_agent_core/entity/llm_provider.py
axmp_ai_agent_core/entity/shared_target.py
axmp_ai_agent_core/entity/user_credential.py
axmp_ai_agent_core/entity/user_rbac.py
axmp_ai_agent_core/exception/__init__.py
axmp_ai_agent_core/exception/db_exceptions.py
axmp_ai_agent_core/exception/service_exceptions.py
axmp_ai_agent_core/filter/agent_profile_history_query.py
axmp_ai_agent_core/filter/agent_profile_query.py
axmp_ai_agent_core/filter/base_search_query.py
axmp_ai_agent_core-0.1.6.dist-info/WHEEL
axmp_ai_agent_core-0.1.6.dist-info/entry_points.txt
axmp_ai_agent_core-0.1.6.dist-info/METADATA
axmp_ai_agent_core-0.1.6.dist-info/RECORD
