Metadata-Version: 2.3
Name: axmp-ai-agent-core
Version: 0.1.6
Summary: Add your description here
Author: Kilsoo Kang
Author-email: Kilsoo Kang <kilsoo75@gmail.com>
Requires-Dist: a2a-sdk>=0.3.20,<0.4.0
Requires-Dist: axmp-ai-agent-spec>=0.1.6
Requires-Dist: axmp-openapi-helper>=0.1.13
Requires-Dist: httpx>=0.28.1
Requires-Dist: langchain-core>=0.3.79,<0.4.0
Requires-Dist: langchain-community>=0.3.31,<0.4.0
Requires-Dist: langchain-openai>=0.3.35,<0.4.0
Requires-Dist: langchain-google-genai>=2.1.9,<3.0.0
Requires-Dist: langchain-anthropic>=0.3.22,<0.4.0
Requires-Dist: langchain-aws==0.2.35
Requires-Dist: langchain-mcp-adapters>=0.1.14,<0.2.0
Requires-Dist: langgraph>=0.6.11,<1.0.0
Requires-Dist: langsmith>=0.4.27,<0.5.0
Requires-Dist: langgraph-checkpoint>=2.1.2,<3.0.0
Requires-Dist: langgraph-checkpoint-postgres>=2.0.25,<3.0.0
Requires-Dist: mcp>=1.14.0
Requires-Dist: motor>=3.7.1
Requires-Dist: psycopg-pool>=3.2.6
Requires-Dist: psycopg[binary]>=3.2.10
Requires-Dist: pydantic-settings>=2.10.1
Requires-Dist: pymongo>=4.15.0
Requires-Dist: python-dotenv>=1.1.1
Requires-Dist: redis>=5.3.1
Requires-Dist: zmp-authentication-provider>=0.3.1
Requires-Python: >=3.12
